{
  "$schema": "https://schema.management.azure.com/schemas/2015-01-01/deploymentTemplate.json#",
  "contentVersion": "1.0.0.0",
  "parameters": {
    "adminUsername": {
      "type": "string",
      "metadata": {
        "description": "User name for the Virtual Machine."
      }
    },
    "adminPassword": {
      "type": "securestring",
      "metadata": {
        "description": "Password for the Virtual Machine."
      }
    },
    "dnsLabelPrefix": {
      "type": "string",
      "metadata": {
        "description": "Unique DNS Name for the Public IP used to access the Virtual Machine."
      }
    },
    "dockerImage": {
      "type": "string",
      "defaultValue": "nginx"
    },
    "dockerPorts" : {
      "type": "string",
      "defaultValue": "80:80"
    },
    "vmSize": {
      "type": "string",
      "allowedValues": [
        "Standard_D1_v2",
        "Standard_D2_v2",
        "Standard_D3_v2",
        "Standard_D4_v2",
        "Standard_D5_v2",
        "Standard_D11_v2",
        "Standard_D12_v2",
        "Standard_D13_v2",
        "Standard_D14_v2",
        "Standard_D15_v2",
        "Standard_DS1_v2",
        "Standard_DS2_v2",
        "Standard_DS3_v2",
        "Standard_DS4_v2",
        "Standard_DS5_v2",
        "Standard_DS11_v2",
        "Standard_DS12_v2",
        "Standard_DS13_v2",
        "Standard_DS14_v2",
        "Standard_DS15_v2"
      ],
      "defaultValue": "Standard_D1_v2"
    }
  },
  "variables": {
    "imagePublisher": "OpenLogic",
    "imageOffer": "CentOs",
    "imageSku": "7.3",
    "nicName": "myVMNic",
    "subnetName": "Subnet",
    "addressPrefix": "10.0.0.0/16",   
    "subnetPrefix": "10.0.0.0/24",
    "publicIPAddressName": "myPublicIP",
    "publicIPAddressType": "Dynamic",
    "vmName": "CentOSVM",
    "virtualNetworkName": "MyVNET",
    "vnetID": "[resourceId('Microsoft.Network/virtualNetworks',variables('virtualNetworkName'))]",
    "subnetRef": "[concat(variables('vnetID'),'/subnets/',variables('subnetName'))]",
    "artifactBaseUrl": "https://raw.githubusercontent.com/petercyli/centos_docker/master/",
    "runDockerScriptUrl": "[concat(variables('artifactBaseUrl'), 'run_docker.sh')]"
  },
  "resources": [
    {
      "apiVersion": "2017-04-01",
      "type": "Microsoft.Network/publicIPAddresses",
      "name": "[variables('publicIPAddressName')]",
      "location": "[resourceGroup().location]",
      "properties": {
        "publicIPAllocationMethod": "[variables('publicIPAddressType')]",
        "dnsSettings": {
          "domainNameLabel": "[parameters('dnsLabelPrefix')]"
        }
      }
    },
    {
      "apiVersion": "2017-04-01",
      "type": "Microsoft.Network/virtualNetworks",
      "name": "[variables('virtualNetworkName')]",
      "location": "[resourceGroup().location]",
      "properties": {
        "addressSpace": {
          "addressPrefixes": [
            "[variables('addressPrefix')]"
          ]
        },
        "subnets": [
          {
            "name": "[variables('subnetName')]",
            "properties": {
              "addressPrefix": "[variables('subnetPrefix')]"
            }
          }
        ]
      }
    },
    {
      "apiVersion": "2017-04-01",
      "type": "Microsoft.Network/networkInterfaces",
      "name": "[variables('nicName')]",
      "location": "[resourceGroup().location]",
      "dependsOn": [
        "[resourceId('Microsoft.Network/publicIPAddresses/', variables('publicIPAddressName'))]",
        "[resourceId('Microsoft.Network/virtualNetworks/', variables('virtualNetworkName'))]"
      ],
      "properties": {
        "ipConfigurations": [
          {
            "name": "ipconfig1",
            "properties": {
              "privateIPAllocationMethod": "Dynamic",
              "publicIPAddress": {
                "id": "[resourceId('Microsoft.Network/publicIPAddresses',variables('publicIPAddressName'))]"
              },
              "subnet": {
                "id": "[variables('subnetRef')]"
              }
            }
          }
        ]
      }
    },
    {
      "apiVersion": "2017-03-30",
      "type": "Microsoft.Compute/virtualMachines",
      "name": "[variables('vmName')]",
      "location": "[resourceGroup().location]",
      "dependsOn": [
        "[resourceId('Microsoft.Network/networkInterfaces/', variables('nicName'))]"
      ],
      "properties": {
        "hardwareProfile": {
          "vmSize": "[parameters('vmSize')]"
        },
        "osProfile": {
          "computerName": "[variables('vmName')]",
          "adminUsername": "[parameters('adminUsername')]",
          "adminPassword": "[parameters('adminPassword')]"
        },
        "storageProfile": {
          "imageReference": {
            "publisher": "[variables('imagePublisher')]",
            "offer": "[variables('imageOffer')]",
            "sku": "[variables('imageSku')]",
            "version": "latest"
          },
          "osDisk": {
            "createOption": "FromImage"
          },
          "dataDisks": [
            {
              "diskSizeGB": 1023,
              "lun": 0,
              "createOption": "Empty"
            }
          ]
        },
        "networkProfile": {
          "networkInterfaces": [
            {
              "id": "[resourceId('Microsoft.Network/networkInterfaces',variables('nicName'))]"
            }
          ]
        }
      }
    },
    {
      "type": "Microsoft.Compute/virtualMachines/extensions",
      "name": "[concat(variables('vmName'),'/CustomScriptExtension')]",
      "location": "[resourceGroup().location]",
      "apiVersion": "2015-06-15",
      "dependsOn": [
        "[concat('Microsoft.Compute/virtualMachines/', variables('vmName'))]"
      ],
      "tags": {
        "displayName": "[concat(variables('vmName'),'setup')]"
      },
      "properties": {
        "publisher": "Microsoft.Azure.Extensions",
        "type": "CustomScript",
        "typeHandlerVersion": "2.0",
        "autoUpgradeMinorVersion": true,
        "settings": {
          "fileUris": [
            "[variables('runDockerScriptUrl')]"
          ],
          "commandToExecute": "[concat('bash ./run_docker.sh ', parameters('dockerImage'), ' ', parameters('dockerPorts'))]"
        }
      }
    }
  ],
  "outputs": {
    "hostname": {
      "type": "string",
      "value": "[reference(variables('publicIPAddressName')).dnsSettings.fqdn]"
    },
    "sshCommand": {
      "type": "string",
      "value": "[concat('ssh ', parameters('adminUsername'), '@', reference(variables('publicIPAddressName')).dnsSettings.fqdn)]"
    }
  }
}
